CHANGES.rst
DESCRIPTION.rst
LICENSE
MANIFEST.in
README.md
setup.py
src/wai.annotations.redis.predictions.egg-info/PKG-INFO
src/wai.annotations.redis.predictions.egg-info/SOURCES.txt
src/wai.annotations.redis.predictions.egg-info/dependency_links.txt
src/wai.annotations.redis.predictions.egg-info/entry_points.txt
src/wai.annotations.redis.predictions.egg-info/namespace_packages.txt
src/wai.annotations.redis.predictions.egg-info/requires.txt
src/wai.annotations.redis.predictions.egg-info/top_level.txt
src/wai/annotations/redis_predictions/isp/__init__.py
src/wai/annotations/redis_predictions/isp/base/__init__.py
src/wai/annotations/redis_predictions/isp/base/component/_BasePredict.py
src/wai/annotations/redis_predictions/isp/base/component/__init__.py
src/wai/annotations/redis_predictions/isp/image_classification/__init__.py
src/wai/annotations/redis_predictions/isp/image_classification/component/_Predict.py
src/wai/annotations/redis_predictions/isp/image_classification/component/__init__.py
src/wai/annotations/redis_predictions/isp/image_classification/specifier/_PredictISPSpecifier.py
src/wai/annotations/redis_predictions/isp/image_classification/specifier/__init__.py
src/wai/annotations/redis_predictions/isp/image_segmentation/__init__.py
src/wai/annotations/redis_predictions/isp/image_segmentation/component/_Predict.py
src/wai/annotations/redis_predictions/isp/image_segmentation/component/__init__.py
src/wai/annotations/redis_predictions/isp/image_segmentation/specifier/_PredictISPSpecifier.py
src/wai/annotations/redis_predictions/isp/image_segmentation/specifier/__init__.py
src/wai/annotations/redis_predictions/isp/object_detection/__init__.py
src/wai/annotations/redis_predictions/isp/object_detection/component/_Predict.py
src/wai/annotations/redis_predictions/isp/object_detection/component/__init__.py
src/wai/annotations/redis_predictions/isp/object_detection/specifier/_PredictISPSpecifier.py
src/wai/annotations/redis_predictions/isp/object_detection/specifier/__init__.py