Metadata-Version: 2.1
Name: wai.annotations.redis.predictions
Version: 1.0.2
Summary: Inline stream processor for making predictions via a Redis backend.
Home-page: https://github.com/waikato-ufdl/wai-annotations-redis-predictions
Author: Peter Reutemann
Author-email: fracpete@waikato.ac.nz
License: Apache License Version 2.0
Platform: UNKNOWN
Classifier: Development Status :: 4 - Beta
Classifier: License :: OSI Approved :: Apache Software License
Classifier: Topic :: Scientific/Engineering :: Mathematics
Classifier: Programming Language :: Python :: 3
License-File: LICENSE
